Eliteproject/__init__.py
Eliteproject/app.py
Eliteproject/assets/__init__.py
Eliteproject/modules/__init__.py
Eliteproject/modules/fimport.py
Eliteproject_STEFANO_BANDINI-2025.0.2.dist-info/LICENSE
Eliteproject_STEFANO_BANDINI-2025.0.2.dist-info/METADATA
Eliteproject_STEFANO_BANDINI-2025.0.2.dist-info/WHEEL
Eliteproject_STEFANO_BANDINI-2025.0.2.dist-info/top_level.txt
Eliteproject_STEFANO_BANDINI-2025.0.2.dist-info/RECORD
